{
  "tabPane": [
    {
      "title": "SmartDashboard",
      "autoPopulate": true,
      "autoPopulatePrefix": "SmartDashboard/",
      "widgetPane": {
        "gridSize": 128.0,
        "showGrid": true,
        "hgap": 16.0,
        "vgap": 16.0,
        "tiles": {
          "2,0": {
            "size": [
              1,
              1
            ],
            "content": {
              "_type": "Text View",
              "_source0": "network_table:///SmartDashboard/SendableChooser[0]/default",
              "_title": "SendableChooser[0]/default"
            }
          },
          "5,4": {
            "size": [
              2,
              1
            ],
            "content": {
              "_type": "Text View",
              "_source0": "network_table:///SmartDashboard/Auto Selector",
              "_title": "Auto Selector"
            }
          },
          "0,1": {
            "size": [
              1,
              1
            ],
            "content": {
              "_type": "Boolean Box",
              "_source0": "network_table:///SmartDashboard/DB/Button 0",
              "_title": "DB/Button 0",
              "Colors/Color when true": "#7CFC00FF",
              "Colors/Color when false": "#8B0000FF"
            }
          },
          "1,1": {
            "size": [
              1,
              1
            ],
            "content": {
              "_type": "Boolean Box",
              "_source0": "network_table:///SmartDashboard/DB/Button 1",
              "_title": "DB/Button 1",
              "Colors/Color when true": "#7CFC00FF",
              "Colors/Color when false": "#8B0000FF"
            }
          },
          "2,1": {
            "size": [
              1,
              1
            ],
            "content": {
              "_type": "Boolean Box",
              "_source0": "network_table:///SmartDashboard/DB/Button 2",
              "_title": "DB/Button 2",
              "Colors/Color when true": "#7CFC00FF",
              "Colors/Color when false": "#8B0000FF"
            }
          },
          "3,1": {
            "size": [
              1,
              1
            ],
            "content": {
              "_type": "Boolean Box",
              "_source0": "network_table:///SmartDashboard/DB/Button 3",
              "_title": "DB/Button 3",
              "Colors/Color when true": "#7CFC00FF",
              "Colors/Color when false": "#8B0000FF"
            }
          },
          "2,2": {
            "size": [
              1,
              1
            ],
            "content": {
              "_type": "Text View",
              "_source0": "network_table:///SmartDashboard/PDP-Temp",
              "_title": "PDP-Temp"
            }
          },
          "3,0": {
            "size": [
              1,
              1
            ],
            "content": {
              "_type": "Text View",
              "_source0": "network_table:///SmartDashboard/PDP-Current-2",
              "_title": "PDP-Current-2"
            }
          },
          "4,0": {
            "size": [
              1,
              1
            ],
            "content": {
              "_type": "Text View",
              "_source0": "network_table:///SmartDashboard/PDP-Current-3",
              "_title": "PDP-Current-3"
            }
          },
          "5,0": {
            "size": [
              1,
              1
            ],
            "content": {
              "_type": "Text View",
              "_source0": "network_table:///SmartDashboard/PDP-Current-4",
              "_title": "PDP-Current-4"
            }
          },
          "6,0": {
            "size": [
              1,
              1
            ],
            "content": {
              "_type": "Text View",
              "_source0": "network_table:///SmartDashboard/PDP-Current-5",
              "_title": "PDP-Current-5"
            }
          },
          "7,0": {
            "size": [
              1,
              1
            ],
            "content": {
              "_type": "Text View",
              "_source0": "network_table:///SmartDashboard/PDP-Current-6",
              "_title": "PDP-Current-6"
            }
          },
          "8,0": {
            "size": [
              1,
              1
            ],
            "content": {
              "_type": "Text View",
              "_source0": "network_table:///SmartDashboard/PDP-Current-7",
              "_title": "PDP-Current-7"
            }
          },
          "9,0": {
            "size": [
              1,
              1
            ],
            "content": {
              "_type": "Text View",
              "_source0": "network_table:///SmartDashboard/PDP-Current-9",
              "_title": "PDP-Current-9"
            }
          },
          "4,1": {
            "size": [
              1,
              1
            ],
            "content": {
              "_type": "Text View",
              "_source0": "network_table:///SmartDashboard/PDP-Current-8",
              "_title": "PDP-Current-8"
            }
          },
          "5,1": {
            "size": [
              1,
              1
            ],
            "content": {
              "_type": "Text View",
              "_source0": "network_table:///SmartDashboard/PDP-Current-10",
              "_title": "PDP-Current-10"
            }
          },
          "6,1": {
            "size": [
              1,
              1
            ],
            "content": {
              "_type": "Text View",
              "_source0": "network_table:///SmartDashboard/PDP-Voltage",
              "_title": "PDP-Voltage"
            }
          },
          "7,1": {
            "size": [
              1,
              1
            ],
            "content": {
              "_type": "Text View",
              "_source0": "network_table:///SmartDashboard/PDP-Current-11",
              "_title": "PDP-Current-11"
            }
          },
          "8,1": {
            "size": [
              1,
              1
            ],
            "content": {
              "_type": "Text View",
              "_source0": "network_table:///SmartDashboard/PDP-Current-12",
              "_title": "PDP-Current-12"
            }
          },
          "9,1": {
            "size": [
              1,
              1
            ],
            "content": {
              "_type": "Text View",
              "_source0": "network_table:///SmartDashboard/PDP-Current-13",
              "_title": "PDP-Current-13"
            }
          },
          "0,2": {
            "size": [
              1,
              1
            ],
            "content": {
              "_type": "Text View",
              "_source0": "network_table:///SmartDashboard/PDP-Current-14",
              "_title": "PDP-Current-14"
            }
          },
          "1,2": {
            "size": [
              1,
              1
            ],
            "content": {
              "_type": "Text View",
              "_source0": "network_table:///SmartDashboard/DB/Slider 2",
              "_title": "DB/Slider 2"
            }
          },
          "3,2": {
            "size": [
              1,
              1
            ],
            "content": {
              "_type": "Text View",
              "_source0": "network_table:///SmartDashboard/DB/Slider 3",
              "_title": "DB/Slider 3"
            }
          },
          "4,2": {
            "size": [
              1,
              1
            ],
            "content": {
              "_type": "Text View",
              "_source0": "network_table:///SmartDashboard/DB/Slider 0",
              "_title": "DB/Slider 0"
            }
          },
          "5,2": {
            "size": [
              1,
              1
            ],
            "content": {
              "_type": "Text View",
              "_source0": "network_table:///SmartDashboard/DB/Slider 1",
              "_title": "DB/Slider 1"
            }
          },
          "6,2": {
            "size": [
              1,
              1
            ],
            "content": {
              "_type": "Text View",
              "_source0": "network_table:///SmartDashboard/DB/String 0",
              "_title": "DB/String 0"
            }
          },
          "7,2": {
            "size": [
              1,
              1
            ],
            "content": {
              "_type": "Text View",
              "_source0": "network_table:///SmartDashboard/DB/String 1",
              "_title": "DB/String 1"
            }
          },
          "8,2": {
            "size": [
              1,
              1
            ],
            "content": {
              "_type": "Text View",
              "_source0": "network_table:///SmartDashboard/DB/String 2",
              "_title": "DB/String 2"
            }
          },
          "9,2": {
            "size": [
              1,
              1
            ],
            "content": {
              "_type": "Text View",
              "_source0": "network_table:///SmartDashboard/DB/String 3",
              "_title": "DB/String 3"
            }
          },
          "0,3": {
            "size": [
              1,
              1
            ],
            "content": {
              "_type": "Text View",
              "_source0": "network_table:///SmartDashboard/DB/String 4",
              "_title": "DB/String 4"
            }
          },
          "1,3": {
            "size": [
              1,
              1
            ],
            "content": {
              "_type": "Text View",
              "_source0": "network_table:///SmartDashboard/DB/String 5",
              "_title": "DB/String 5"
            }
          },
          "2,3": {
            "size": [
              1,
              1
            ],
            "content": {
              "_type": "Text View",
              "_source0": "network_table:///SmartDashboard/DB/String 6",
              "_title": "DB/String 6"
            }
          },
          "3,3": {
            "size": [
              1,
              1
            ],
            "content": {
              "_type": "Text View",
              "_source0": "network_table:///SmartDashboard/DB/String 7",
              "_title": "DB/String 7"
            }
          },
          "4,3": {
            "size": [
              1,
              1
            ],
            "content": {
              "_type": "Text View",
              "_source0": "network_table:///SmartDashboard/DB/String 8",
              "_title": "DB/String 8"
            }
          },
          "5,3": {
            "size": [
              1,
              1
            ],
            "content": {
              "_type": "Text View",
              "_source0": "network_table:///SmartDashboard/DB/String 9",
              "_title": "DB/String 9"
            }
          },
          "6,3": {
            "size": [
              1,
              1
            ],
            "content": {
              "_type": "Text View",
              "_source0": "network_table:///SmartDashboard/PDP-Current-0",
              "_title": "PDP-Current-0"
            }
          },
          "7,3": {
            "size": [
              1,
              1
            ],
            "content": {
              "_type": "Text View",
              "_source0": "network_table:///SmartDashboard/PDP-Current-1",
              "_title": "PDP-Current-1"
            }
          },
          "10,0": {
            "size": [
              1,
              1
            ],
            "content": {
              "_type": "Text View",
              "_source0": "network_table:///SmartDashboard/encoder_left",
              "_title": "encoder_left"
            }
          },
          "11,0": {
            "size": [
              1,
              1
            ],
            "content": {
              "_type": "Text View",
              "_source0": "network_table:///SmartDashboard/encoder_right",
              "_title": "encoder_right"
            }
          },
          "0,0": {
            "size": [
              1,
              1
            ],
            "content": {
              "_type": "Text View",
              "_source0": "network_table:///SmartDashboard/SendableChooser[1]/selected",
              "_title": "SendableChooser[1]/selected"
            }
          },
          "1,0": {
            "size": [
              1,
              1
            ],
            "content": {
              "_type": "Text View",
              "_source0": "network_table:///SmartDashboard/SendableChooser[1]/default",
              "_title": "SendableChooser[1]/default"
            }
          },
          "12,0": {
            "size": [
              1,
              1
            ],
            "content": {
              "_type": "Text View",
              "_source0": "network_table:///SmartDashboard/SendableChooser[1]/active",
              "_title": "SendableChooser[1]/active"
            }
          },
          "10,1": {
            "size": [
              1,
              1
            ],
            "content": {
              "_type": "ComboBox Chooser",
              "_source0": "network_table:///SmartDashboard/SendableChooser[1]",
              "_title": "SendableChooser[1]"
            }
          },
          "11,1": {
            "size": [
              1,
              1
            ],
            "content": {
              "_type": "Text View",
              "_source0": "network_table:///SmartDashboard/shoulderPosition",
              "_title": "shoulderPosition"
            }
          },
          "12,1": {
            "size": [
              1,
              1
            ],
            "content": {
              "_type": "Text View",
              "_source0": "network_table:///SmartDashboard/shoulderVelocity",
              "_title": "shoulderVelocity"
            }
          },
          "10,2": {
            "size": [
              1,
              1
            ],
            "content": {
              "_type": "Text View",
              "_source0": "network_table:///SmartDashboard/shoulderTarget",
              "_title": "shoulderTarget"
            }
          },
          "11,2": {
            "size": [
              1,
              1
            ],
            "content": {
              "_type": "Text View",
              "_source0": "network_table:///SmartDashboard/shoulderOutput",
              "_title": "shoulderOutput"
            }
          },
          "12,2": {
            "size": [
              1,
              1
            ],
            "content": {
              "_type": "Boolean Box",
              "_source0": "network_table:///SmartDashboard/forearmCanStop",
              "_title": "forearmCanStop",
              "Colors/Color when true": "#7CFC00FF",
              "Colors/Color when false": "#8B0000FF"
            }
          },
          "8,3": {
            "size": [
              1,
              1
            ],
            "content": {
              "_type": "ComboBox Chooser",
              "_source0": "network_table:///SmartDashboard/SendableChooser[0]",
              "_title": "SendableChooser[0]"
            }
          },
          "9,3": {
            "size": [
              1,
              1
            ],
            "content": {
              "_type": "Text View",
              "_source0": "network_table:///SmartDashboard/power panel/Chan0",
              "_title": "power panel/Chan0"
            }
          },
          "10,3": {
            "size": [
              1,
              1
            ],
            "content": {
              "_type": "Text View",
              "_source0": "network_table:///SmartDashboard/power panel/Chan1",
              "_title": "power panel/Chan1"
            }
          },
          "11,3": {
            "size": [
              1,
              1
            ],
            "content": {
              "_type": "Text View",
              "_source0": "network_table:///SmartDashboard/power panel/Chan2",
              "_title": "power panel/Chan2"
            }
          },
          "12,3": {
            "size": [
              1,
              1
            ],
            "content": {
              "_type": "Text View",
              "_source0": "network_table:///SmartDashboard/power panel/Chan3",
              "_title": "power panel/Chan3"
            }
          },
          "0,4": {
            "size": [
              1,
              1
            ],
            "content": {
              "_type": "Text View",
              "_source0": "network_table:///SmartDashboard/power panel/Chan4",
              "_title": "power panel/Chan4"
            }
          },
          "1,4": {
            "size": [
              1,
              1
            ],
            "content": {
              "_type": "Text View",
              "_source0": "network_table:///SmartDashboard/power panel/Chan5",
              "_title": "power panel/Chan5"
            }
          },
          "2,4": {
            "size": [
              1,
              1
            ],
            "content": {
              "_type": "Text View",
              "_source0": "network_table:///SmartDashboard/power panel/Chan6",
              "_title": "power panel/Chan6"
            }
          },
          "3,4": {
            "size": [
              1,
              1
            ],
            "content": {
              "_type": "Text View",
              "_source0": "network_table:///SmartDashboard/power panel/Chan7",
              "_title": "power panel/Chan7"
            }
          },
          "4,4": {
            "size": [
              1,
              1
            ],
            "content": {
              "_type": "Text View",
              "_source0": "network_table:///SmartDashboard/power panel/Chan8",
              "_title": "power panel/Chan8"
            }
          },
          "7,4": {
            "size": [
              1,
              1
            ],
            "content": {
              "_type": "Text View",
              "_source0": "network_table:///SmartDashboard/power panel/Chan9",
              "_title": "power panel/Chan9"
            }
          },
          "8,4": {
            "size": [
              1,
              1
            ],
            "content": {
              "_type": "Text View",
              "_source0": "network_table:///SmartDashboard/power panel/Chan10",
              "_title": "power panel/Chan10"
            }
          },
          "9,4": {
            "size": [
              1,
              1
            ],
            "content": {
              "_type": "Text View",
              "_source0": "network_table:///SmartDashboard/power panel/Chan11",
              "_title": "power panel/Chan11"
            }
          },
          "10,4": {
            "size": [
              1,
              1
            ],
            "content": {
              "_type": "Text View",
              "_source0": "network_table:///SmartDashboard/power panel/Chan12",
              "_title": "power panel/Chan12"
            }
          },
          "11,4": {
            "size": [
              1,
              1
            ],
            "content": {
              "_type": "Text View",
              "_source0": "network_table:///SmartDashboard/power panel/Chan13",
              "_title": "power panel/Chan13"
            }
          },
          "12,4": {
            "size": [
              1,
              1
            ],
            "content": {
              "_type": "Text View",
              "_source0": "network_table:///SmartDashboard/power panel/Chan14",
              "_title": "power panel/Chan14"
            }
          },
          "0,5": {
            "size": [
              1,
              1
            ],
            "content": {
              "_type": "Text View",
              "_source0": "network_table:///SmartDashboard/power panel/Chan15",
              "_title": "power panel/Chan15"
            }
          },
          "1,5": {
            "size": [
              1,
              1
            ],
            "content": {
              "_type": "Text View",
              "_source0": "network_table:///SmartDashboard/power panel/Voltage",
              "_title": "power panel/Voltage"
            }
          },
          "2,5": {
            "size": [
              1,
              1
            ],
            "content": {
              "_type": "Text View",
              "_source0": "network_table:///SmartDashboard/power panel/TotalCurrent",
              "_title": "power panel/TotalCurrent"
            }
          },
          "3,5": {
            "size": [
              1,
              1
            ],
            "content": {
              "_type": "Boolean Box",
              "_source0": "network_table:///SmartDashboard/power panel/SwitchableChannel",
              "_title": "power panel/SwitchableChannel",
              "Colors/Color when true": "#7CFC00FF",
              "Colors/Color when false": "#8B0000FF"
            }
          },
          "4,5": {
            "size": [
              1,
              1
            ],
            "content": {
              "_type": "Text View",
              "_source0": "network_table:///SmartDashboard/accel X",
              "_title": "accel X"
            }
          },
          "5,5": {
            "size": [
              1,
              1
            ],
            "content": {
              "_type": "Text View",
              "_source0": "network_table:///SmartDashboard/accel Y",
              "_title": "accel Y"
            }
          },
          "6,5": {
            "size": [
              1,
              1
            ],
            "content": {
              "_type": "Text View",
              "_source0": "network_table:///SmartDashboard/accel Z",
              "_title": "accel Z"
            }
          },
          "7,5": {
            "size": [
              1,
              1
            ],
            "content": {
              "_type": "Text View",
              "_source0": "network_table:///SmartDashboard/Robot Mode",
              "_title": "Robot Mode"
            }
          },
          "8,5": {
            "size": [
              1,
              1
            ],
            "content": {
              "_type": "Boolean Box",
              "_source0": "network_table:///SmartDashboard/Autosteer",
              "_title": "Autosteer",
              "Colors/Color when true": "#7CFC00FF",
              "Colors/Color when false": "#8B0000FF"
            }
          },
          "9,5": {
            "size": [
              1,
              1
            ],
            "content": {
              "_type": "Boolean Box",
              "_source0": "network_table:///SmartDashboard/Valid Target",
              "_title": "Valid Target",
              "Colors/Color when true": "#7CFC00FF",
              "Colors/Color when false": "#8B0000FF"
            }
          },
          "10,5": {
            "size": [
              1,
              1
            ],
            "content": {
              "_type": "Text View",
              "_source0": "network_table:///SmartDashboard/Target Angle",
              "_title": "Target Angle"
            }
          },
          "11,5": {
            "size": [
              1,
              1
            ],
            "content": {
              "_type": "Text View",
              "_source0": "network_table:///SmartDashboard/gyro",
              "_title": "gyro"
            }
          },
          "12,5": {
            "size": [
              1,
              1
            ],
            "content": {
              "_type": "Text View",
              "_source0": "network_table:///SmartDashboard/forearmPosition",
              "_title": "forearmPosition"
            }
          }
        }
      }
    },
    {
      "title": "LiveWindow",
      "autoPopulate": true,
      "autoPopulatePrefix": "LiveWindow/",
      "widgetPane": {
        "gridSize": 128.0,
        "showGrid": true,
        "hgap": 16.0,
        "vgap": 16.0,
        "tiles": {
          "0,0": {
            "size": [
              2,
              4
            ],
            "content": {
              "_type": "Subsystem Layout",
              "_source0": "network_table:///LiveWindow/Ungrouped",
              "_title": "Ungrouped",
              "Layout/Label position": "BOTTOM",
              "_children": [
                {
                  "_type": "Gyro",
                  "_source0": "network_table:///LiveWindow/Ungrouped/ADXRS450_Gyro[0]",
                  "_title": "ADXRS450_Gyro[0]",
                  "Visuals/Major tick spacing": 45.0,
                  "Visuals/Starting angle": 180.0,
                  "Visuals/Show tick mark ring": true,
                  "Visuals/Counter clockwise": false
                },
                {
                  "_type": "PID Controller",
                  "_source0": "network_table:///LiveWindow/Ungrouped/PIDController[1]",
                  "_title": "PIDController[1]"
                },
                {
                  "_type": "PID Controller",
                  "_source0": "network_table:///LiveWindow/Ungrouped/PIDController[2]",
                  "_title": "PIDController[2]"
                },
                {
                  "_type": "PDP",
                  "_source0": "network_table:///LiveWindow/Ungrouped/PowerDistributionPanel[0]",
                  "_title": "PowerDistributionPanel[0]",
                  "Visuals/Show voltage and current values": true
                },
                {
                  "_type": "PDP",
                  "_source0": "network_table:///LiveWindow/Ungrouped/PowerDistributionPanel[25]",
                  "_title": "PowerDistributionPanel[25]",
                  "Visuals/Show voltage and current values": true
                },
                {
                  "_type": "Speed Controller",
                  "_source0": "network_table:///LiveWindow/Ungrouped/Talon SRX [4]",
                  "_title": "Talon SRX [4]",
                  "Visuals/Orientation": "HORIZONTAL"
                },
                {
                  "_type": "Speed Controller",
                  "_source0": "network_table:///LiveWindow/Ungrouped/Talon SRX [2]",
                  "_title": "Talon SRX [2]",
                  "Visuals/Orientation": "HORIZONTAL"
                },
                {
                  "_type": "PID Controller",
                  "_source0": "network_table:///LiveWindow/Ungrouped/PIDController[3]",
                  "_title": "PIDController[3]"
                },
                {
                  "_type": "Text View",
                  "_source0": "network_table:///LiveWindow/Ungrouped/PowerDistribution[0]/Chan0",
                  "_title": "PowerDistribution[0]/Chan0"
                },
                {
                  "_type": "Text View",
                  "_source0": "network_table:///LiveWindow/Ungrouped/PowerDistribution[0]/Chan1",
                  "_title": "PowerDistribution[0]/Chan1"
                },
                {
                  "_type": "Text View",
                  "_source0": "network_table:///LiveWindow/Ungrouped/PowerDistribution[0]/Chan2",
                  "_title": "PowerDistribution[0]/Chan2"
                },
                {
                  "_type": "Text View",
                  "_source0": "network_table:///LiveWindow/Ungrouped/PowerDistribution[0]/Chan3",
                  "_title": "PowerDistribution[0]/Chan3"
                },
                {
                  "_type": "Text View",
                  "_source0": "network_table:///LiveWindow/Ungrouped/PowerDistribution[0]/Chan4",
                  "_title": "PowerDistribution[0]/Chan4"
                },
                {
                  "_type": "Text View",
                  "_source0": "network_table:///LiveWindow/Ungrouped/PowerDistribution[0]/Chan5",
                  "_title": "PowerDistribution[0]/Chan5"
                },
                {
                  "_type": "Text View",
                  "_source0": "network_table:///LiveWindow/Ungrouped/PowerDistribution[0]/Chan6",
                  "_title": "PowerDistribution[0]/Chan6"
                },
                {
                  "_type": "Text View",
                  "_source0": "network_table:///LiveWindow/Ungrouped/PowerDistribution[0]/Chan7",
                  "_title": "PowerDistribution[0]/Chan7"
                },
                {
                  "_type": "Text View",
                  "_source0": "network_table:///LiveWindow/Ungrouped/PowerDistribution[0]/Chan8",
                  "_title": "PowerDistribution[0]/Chan8"
                },
                {
                  "_type": "Text View",
                  "_source0": "network_table:///LiveWindow/Ungrouped/PowerDistribution[0]/Chan9",
                  "_title": "PowerDistribution[0]/Chan9"
                },
                {
                  "_type": "Text View",
                  "_source0": "network_table:///LiveWindow/Ungrouped/PowerDistribution[0]/Voltage",
                  "_title": "PowerDistribution[0]/Voltage"
                },
                {
                  "_type": "Text View",
                  "_source0": "network_table:///LiveWindow/Ungrouped/PowerDistribution[0]/TotalCurrent",
                  "_title": "PowerDistribution[0]/TotalCurrent"
                },
                {
                  "_type": "Boolean Box",
                  "_source0": "network_table:///LiveWindow/Ungrouped/PowerDistribution[0]/SwitchableChannel",
                  "_title": "PowerDistribution[0]/SwitchableChannel",
                  "Colors/Color when true": "#7CFC00FF",
                  "Colors/Color when false": "#8B0000FF"
                },
                {
                  "_type": "3-Axis Accelerometer",
                  "_source0": "network_table:///LiveWindow/Ungrouped/BuiltInAccel[0]",
                  "_title": "BuiltInAccel[0]",
                  "Accelerometer/Range": "k16G",
                  "Visuals/Show value": true,
                  "Visuals/Precision": 2,
                  "Visuals/Show tick marks": false
                },
                {
                  "_type": "Text View",
                  "_source0": "network_table:///LiveWindow/Ungrouped/PWMTalonSRX[3]/Value",
                  "_title": "PWMTalonSRX[3]/Value"
                }
              ]
            }
          }
        }
      }
    },
    {
      "title": "PowerBoard",
      "autoPopulate": false,
      "autoPopulatePrefix": "",
      "widgetPane": {
        "gridSize": 164.0,
        "showGrid": true,
        "hgap": 32.0,
        "vgap": 32.0,
        "tiles": {
          "0,0": {
            "size": [
              5,
              3
            ],
            "content": {
              "_type": "Graph",
              "_source0": "network_table:///SmartDashboard/PDP-Current-2",
              "_source1": "network_table:///SmartDashboard/PDP-Current-3",
              "_source2": "network_table:///SmartDashboard/PDP-Current-4",
              "_source3": "network_table:///SmartDashboard/PDP-Current-5",
              "_source4": "network_table:///SmartDashboard/PDP-Current-6",
              "_source5": "network_table:///SmartDashboard/PDP-Current-7",
              "_source6": "network_table:///SmartDashboard/PDP-Current-9",
              "_source7": "network_table:///SmartDashboard/PDP-Current-8",
              "_source8": "network_table:///SmartDashboard/PDP-Current-10",
              "_source9": "network_table:///SmartDashboard/PDP-Current-11",
              "_source10": "network_table:///SmartDashboard/PDP-Current-12",
              "_source11": "network_table:///SmartDashboard/PDP-Current-13",
              "_source12": "network_table:///SmartDashboard/PDP-Current-14",
              "_source13": "network_table:///SmartDashboard/PDP-Current-0",
              "_source14": "network_table:///SmartDashboard/PDP-Current-1",
              "_title": "Channels",
              "Graph/Visible time": 100.0,
              "Graph/X-axis auto scrolling": true,
              "Y-axis/Automatic bounds": false,
              "Y-axis/Upper bound": 12.0,
              "Y-axis/Lower bound": 0.0,
              "Y-axis/Unit": "ul"
            }
          },
          "5,0": {
            "size": [
              2,
              2
            ],
            "content": {
              "_type": "Graph",
              "_source0": "network_table:///SmartDashboard/PDP-Voltage",
              "_title": "Graph",
              "Graph/Visible time": 30.0,
              "Graph/X-axis auto scrolling": true,
              "Y-axis/Automatic bounds": true,
              "Y-axis/Upper bound": 1.0,
              "Y-axis/Lower bound": -1.0,
              "Y-axis/Unit": "ul"
            }
          },
          "5,2": {
            "size": [
              2,
              1
            ],
            "content": {
              "_type": "Simple Dial",
              "_source0": "network_table:///SmartDashboard/PDP-Temp",
              "_title": "PDP Temp",
              "Range/Min": 0.0,
              "Range/Max": 100.0,
              "Visuals/Show value": true
            }
          }
        }
      }
    },
    {
      "title": "Driver station",
      "autoPopulate": false,
      "autoPopulatePrefix": "",
      "widgetPane": {
        "gridSize": 64.0,
        "showGrid": true,
        "hgap": 16.0,
        "vgap": 16.0,
        "tiles": {
          "2,2": {
            "size": [
              7,
              6
            ],
            "content": {
              "_type": "Camera Stream",
              "_title": "Camera Stream",
              "Crosshair/Show crosshair": true,
              "Crosshair/Crosshair color": "#FFFFFFFF",
              "Controls/Show controls": true,
              "Controls/Rotation": "NONE",
              "compression": -1.0,
              "fps": -1,
              "imageWidth": -1,
              "imageHeight": -1
            }
          },
          "13,1": {
            "size": [
              2,
              2
            ],
            "content": {
              "_type": "ComboBox Chooser",
              "_title": "ComboBox Chooser"
            }
          },
          "0,4": {
            "size": [
              2,
              2
            ],
            "content": {
              "_type": "Boolean Box",
              "_title": "Boolean Box",
              "Colors/Color when true": "#7CFC00FF",
              "Colors/Color when false": "#8B0000FF"
            }
          },
          "2,0": {
            "size": [
              5,
              2
            ],
            "content": {
              "_type": "Basic FMS Info",
              "_title": "Basic FMS Info"
            }
          },
          "9,0": {
            "size": [
              3,
              3
            ],
            "content": {
              "_type": "Gyro",
              "_title": "Gyro",
              "Visuals/Major tick spacing": 45.0,
              "Visuals/Starting angle": 180.0,
              "Visuals/Show tick mark ring": true,
              "Visuals/Counter clockwise": false
            }
          },
          "7,0": {
            "size": [
              2,
              2
            ],
            "content": {
              "_type": "Simple Dial",
              "_title": "Simple Dial",
              "Range/Min": 0.0,
              "Range/Max": 100.0,
              "Visuals/Show value": true
            }
          },
          "0,6": {
            "size": [
              2,
              2
            ],
            "content": {
              "_type": "Boolean Box",
              "_title": "Boolean Box",
              "Colors/Color when true": "#7CFC00FF",
              "Colors/Color when false": "#8B0000FF"
            }
          },
          "10,4": {
            "size": [
              4,
              3
            ],
            "content": {
              "_type": "Text View",
              "_source0": "network_table:///SmartDashboard/Auto Selector",
              "_title": "/SmartDashboard/Auto Selector"
            }
          },
          "15,4": {
            "size": [
              5,
              2
            ],
            "content": {
              "_type": "ComboBox Chooser",
              "_source0": "network_table:///SmartDashboard/SendableChooser[1]",
              "_title": "Auto selector"
            }
          }
        }
      }
    },
    {
      "title": "Auto station",
      "autoPopulate": false,
      "autoPopulatePrefix": "",
      "widgetPane": {
        "gridSize": 64.0,
        "showGrid": true,
        "hgap": 16.0,
        "vgap": 16.0,
        "tiles": {
          "6,4": {
            "size": [
              4,
              4
            ],
            "content": {
              "_type": "Gyro",
              "_source0": "network_table:///LiveWindow/Ungrouped/ADXRS450_Gyro[0]",
              "_title": "Gyro",
              "Visuals/Major tick spacing": 45.0,
              "Visuals/Starting angle": 180.0,
              "Visuals/Show tick mark ring": true,
              "Visuals/Counter clockwise": false
            }
          },
          "0,2": {
            "size": [
              4,
              2
            ],
            "content": {
              "_type": "ComboBox Chooser",
              "_source0": "network_table:///SmartDashboard/SendableChooser[1]",
              "_title": "ComboBox Chooser"
            }
          },
          "0,4": {
            "size": [
              6,
              4
            ],
            "content": {
              "_type": "Camera Stream",
              "_title": "Camera Stream",
              "Crosshair/Show crosshair": true,
              "Crosshair/Crosshair color": "#FFFFFFFF",
              "Controls/Show controls": true,
              "Controls/Rotation": "NONE",
              "compression": -1.0,
              "fps": -1,
              "imageWidth": -1,
              "imageHeight": -1
            }
          },
          "4,2": {
            "size": [
              2,
              2
            ],
            "content": {
              "_type": "Boolean Box",
              "_title": "Boolean Box",
              "Colors/Color when true": "#7CFC00FF",
              "Colors/Color when false": "#8B0000FF"
            }
          },
          "8,2": {
            "size": [
              2,
              2
            ],
            "content": {
              "_type": "Number Bar",
              "_source0": "network_table:///SmartDashboard/encoder_right",
              "_title": "Right",
              "Range/Min": -1.0,
              "Range/Max": 1.0,
              "Range/Center": 0.0,
              "Visuals/Num tick marks": 5,
              "Visuals/Show text": true
            }
          },
          "6,2": {
            "size": [
              2,
              2
            ],
            "content": {
              "_type": "Number Bar",
              "_source0": "network_table:///SmartDashboard/encoder_left",
              "_title": "Left",
              "Range/Min": -1.0,
              "Range/Max": 1.0,
              "Range/Center": 0.0,
              "Visuals/Num tick marks": 5,
              "Visuals/Show text": true
            }
          },
          "0,8": {
            "size": [
              10,
              2
            ],
            "content": {
              "_type": "Voltage View",
              "_title": "Voltage View",
              "Range/Min": 0.0,
              "Range/Max": 5.0,
              "Range/Center": 0.0,
              "Visuals/Orientation": "HORIZONTAL",
              "Visuals/Number of tick marks": 5
            }
          }
        }
      }
    },
    {
      "title": "debug",
      "autoPopulate": false,
      "autoPopulatePrefix": "",
      "widgetPane": {
        "gridSize": 128.0,
        "showGrid": true,
        "hgap": 16.0,
        "vgap": 16.0,
        "tiles": {
          "3,1": {
            "size": [
              3,
              2
            ],
            "content": {
              "_type": "Number Bar",
              "_source0": "network_table:///SmartDashboard/encoder_left",
              "_title": "Left encoder",
              "Range/Min": -1.0,
              "Range/Max": 1.0,
              "Range/Center": 0.0,
              "Visuals/Num tick marks": 5,
              "Visuals/Show text": true
            }
          },
          "0,1": {
            "size": [
              3,
              2
            ],
            "content": {
              "_type": "Number Bar",
              "_source0": "network_table:///SmartDashboard/encoder_right",
              "_title": "Right encoder",
              "Range/Min": -1.0,
              "Range/Max": 1.0,
              "Range/Center": 0.0,
              "Visuals/Num tick marks": 5,
              "Visuals/Show text": true
            }
          },
          "6,1": {
            "size": [
              2,
              2
            ],
            "content": {
              "_type": "Gyro",
              "_source0": "network_table:///LiveWindow/Ungrouped/ADXRS450_Gyro[0]",
              "_title": "LiveWindow/Ungrouped/ADXRS450_Gyro[0]",
              "Visuals/Major tick spacing": 45.0,
              "Visuals/Starting angle": 180.0,
              "Visuals/Show tick mark ring": true,
              "Visuals/Counter clockwise": false
            }
          },
          "5,3": {
            "size": [
              3,
              1
            ],
            "content": {
              "_type": "ComboBox Chooser",
              "_source0": "network_table:///SmartDashboard/SendableChooser[0]",
              "_title": "/SmartDashboard/SendableChooser[0]"
            }
          },
          "8,1": {
            "size": [
              5,
              5
            ],
            "content": {
              "_type": "Network Table Tree",
              "_source0": "network_table:///LiveWindow/Ungrouped/PowerDistribution[0]",
              "_title": "/LiveWindow/Ungrouped/PowerDistribution[0]"
            }
          },
          "0,5": {
            "size": [
              8,
              1
            ],
            "content": {
              "_type": "3-Axis Accelerometer",
              "_source0": "network_table:///LiveWindow/Ungrouped/BuiltInAccel[0]",
              "_title": "/LiveWindow/Ungrouped/BuiltInAccel[0]",
              "Accelerometer/Range": "k16G",
              "Visuals/Show value": true,
              "Visuals/Precision": 2,
              "Visuals/Show tick marks": false
            }
          },
          "0,3": {
            "size": [
              1,
              1
            ],
            "content": {
              "_type": "Boolean Box",
              "_source0": "network_table:///SmartDashboard/hasBall",
              "_title": "/SmartDashboard/hasBall",
              "Colors/Color when true": "#7CFC00FF",
              "Colors/Color when false": "#8B0000FF"
            }
          }
        }
      }
    }
  ],
  "windowGeometry": {
    "x": -8.0,
    "y": -8.0,
    "width": 1936.0,
    "height": 1056.0
  }
}